{
  "entityType" : "ENTITY_GROUP",
  "entity" : {
    "additionalInfo" : null,
    "configuration" : {
      "columns" : [ {
        "type" : "ENTITY_FIELD",
        "key" : "created_time",
        "sortOrder" : "DESC"
      }, {
        "type" : "ENTITY_FIELD",
        "key" : "name",
        "sortOrder" : "NONE"
      }, {
        "type" : "ENTITY_FIELD",
        "key" : "type",
        "sortOrder" : "NONE"
      } ],
      "settings" : { },
      "actions" : { }
    },
    "edgeGroupAll" : false,
    "externalId" : {
      "entityType" : "ENTITY_GROUP",
      "id" : "1bc8cdf0-4a18-11ef-8e6e-2d58a4dcc0ca"
    },
    "groupAll" : true,
    "id" : {
      "entityType" : "ENTITY_GROUP",
      "id" : "1bc8cdf0-4a18-11ef-8e6e-2d58a4dcc0ca"
    },
    "name" : "All",
    "ownerId" : {
      "entityType" : "TENANT",
      "id" : "1b98bd40-4a18-11ef-8e6e-2d58a4dcc0ca"
    },
    "type" : "ENTITY_VIEW"
  },
  "relations" : [ ],
  "attributes" : {
    "SERVER_SCOPE" : [ ]
  },
  "groupEntities" : true
}